sample/__init__.py
sample/sample.pypy310-pp73-aarch64-linux-gnu.so
sampleproject_rs-0.2.2.dist-info/METADATA
sampleproject_rs-0.2.2.dist-info/WHEEL
sampleproject_rs-0.2.2.dist-info/entry_points.txt
sampleproject_rs-0.2.2.dist-info/licenses/LICENSE
sampleproject_rs-0.2.2.dist-info/RECORD
