Metadata-Version: 2.4
Name: sampleproject-rs
Version: 0.2.2
Classifier: Development Status :: 3 - Alpha
Classifier: Intended Audience :: Developers
Classifier: Topic :: Software Development :: Build Tools
Classifier: License :: OSI Approved :: MIT License
Classifier: Programming Language :: Python :: 3
Classifier: Programming Language :: Python :: 3.10
Classifier: Programming Language :: Python :: 3.11
Classifier: Programming Language :: Python :: 3.12
Classifier: Programming Language :: Python :: 3.13
Classifier: Programming Language :: Python :: 3 :: Only
Requires-Dist: pytest ; extra == 'test'
Provides-Extra: dev
Provides-Extra: test
License-File: LICENSE
Summary: A sample Python project from Rust binary
Keywords: sample,maturin,development
Author-email: ftnext <takuyafjp+develop@gmail.com>
Requires-Python: >=3.10
Project-URL: Homepage, https://github.com/ftnext/sampleproject-rs
Project-URL: Bug Reports, https://github.com/ftnext/sampleproject-rs/issues
Project-URL: Source, https://github.com/ftnext/sampleproject-rs/
